{
  "description": "项目配置文件",
  "packOptions": {
    "ignore": []
  },
  "setting": {
    "urlCheck": false,
    "es6": true,
    "enhance": true,
    "postcss": true,
    "preloadBackgroundData": false,
    "minified": true,
    "newFeature": true,
    "coverView": true,
    "nodeModules": true,
    "autoAudits": false,
    "showShadowRootInWxmlPanel": true,
    "scopeDataCheck": false,
    "checkInvalidKey": true,
    "checkSiteMap": true,
    "uploadWithSourceMap": true,
    "babelSetting": {
      "ignore": [],
      "disablePlugins": [],
      "outputPath": ""
    },
    "useIsolateContext": true,
    "useCompilerModule": true,
    "userConfirmedUseCompilerModuleSwitch": false,
    "packNpmManually": false,
    "packNpmRelationList": [],
    "useMultiFrameRuntime": false,
    "useApiHook": true
  },
  "compileType": "miniprogram",
  "libVersion": "2.13.0",
  "appid": "wxd4728d868b084d7a",
  "projectname": "big_training",
  "debugOptions": {
    "hidedInDevtools": []
  },
  "isGameTourist": false,
  "simulatorType": "wechat",
  "simulatorPluginLibVersion": {},
  "condition": {
    "search": {
      "current": -1,
      "list": []
    },
    "conversation": {
      "current": -1,
      "list": []
    },
    "plugin": {
      "current": -1,
      "list": []
    },
    "game": {
      "currentL": -1,
      "list": []
    },
    "gamePlugin": {
      "current": -1,
      "list": []
    },
    "miniprogram": {
      "current": -1,
      "list": [
        {
          "id": 0,
          "name": "pages/fight/index",
          "pathName": "pages/fight/index",
          "query": "",
          "scene": null
        }
      ]
    }
  }
}